grotradeflow/__init__.py
grotradeflow/client.py
grotradeflow/environment.py
grotradeflow/core/__init__.py
grotradeflow/core/api_error.py
grotradeflow/core/client_wrapper.py
grotradeflow/core/datetime_utils.py
grotradeflow/core/jsonable_encoder.py
grotradeflow/core/remove_none_from_dict.py
grotradeflow/errors/__init__.py
grotradeflow/errors/bad_request_error.py
grotradeflow/errors/not_found_error.py
grotradeflow/resources/__init__.py
grotradeflow/resources/fern/__init__.py
grotradeflow/resources/fern/client.py
grotradeflow-0.0.153.dist-info/METADATA
grotradeflow-0.0.153.dist-info/WHEEL
grotradeflow-0.0.153.dist-info/licenses/LICENSE
grotradeflow-0.0.153.dist-info/RECORD
