Metadata-Version: 2.1
Name: grotradeflow
Version: 0.0.153
Summary: Python client library grotradeflow
Project-URL: Repository, https://github.com/gro-intelligence/gro-internal/tree/main/apis/trade-flow/python
Author-email: Jackson Sargent <jackson.sargent@gro-intelligence.com>
License-Expression: MIT
License-File: LICENSE
Classifier: License :: OSI Approved :: MIT License
Classifier: Operating System :: OS Independent
Classifier: Programming Language :: Python :: 3
Requires-Python: >=3.7
Requires-Dist: httpx>=0.21.2
Requires-Dist: pydantic<2.0.0,>=1.9.2
